tangledweb/__init__.py
tangledweb/tangledweb.py
tangledweb/modules/__init__.py
tangledweb-1.0.0.dist-info/LICENSE
tangledweb-1.0.0.dist-info/METADATA
tangledweb-1.0.0.dist-info/WHEEL
tangledweb-1.0.0.dist-info/top_level.txt
tangledweb-1.0.0.dist-info/RECORD
